featuremanagement/__init__.py
featuremanagement/_defaultfilters.py
featuremanagement/_featurefilters.py
featuremanagement/_featuremanager.py
featuremanagement/_featuremanagerbase.py
featuremanagement/_version.py
featuremanagement/py.typed
featuremanagement/_models/__init__.py
featuremanagement/_models/_allocation.py
featuremanagement/_models/_constants.py
featuremanagement/_models/_evaluation_event.py
featuremanagement/_models/_feature_conditions.py
featuremanagement/_models/_feature_flag.py
featuremanagement/_models/_targeting_context.py
featuremanagement/_models/_telemetry.py
featuremanagement/_models/_variant.py
featuremanagement/_models/_variant_assignment_reason.py
featuremanagement/_models/_variant_reference.py
featuremanagement/_time_window_filter/__init__.py
featuremanagement/_time_window_filter/_models.py
featuremanagement/_time_window_filter/_recurrence_evaluator.py
featuremanagement/_time_window_filter/_recurrence_validator.py
featuremanagement/aio/__init__.py
featuremanagement/aio/_defaultfilters.py
featuremanagement/aio/_featurefilters.py
featuremanagement/aio/_featuremanager.py
featuremanagement/azuremonitor/__init__.py
featuremanagement/azuremonitor/_send_telemetry.py
featuremanagement-2.1.0.dist-info/licenses/LICENSE
tests/__init__.py
tests/test_default_feature_flags.py
tests/test_default_feature_flags_async.py
tests/test_feature_manager.py
tests/test_feature_manager_async.py
tests/test_feature_manager_refresh.py
tests/test_feature_variants.py
tests/test_feature_variants_async.py
tests/test_send_telemetry_appinsights.py
tests/time_window_filter/test_recurrence_evaluator.py
tests/time_window_filter/test_recurrence_validator.py
tests/time_window_filter/test_time_window_filter_models.py
tests/validation_tests/test_json_validations.py
featuremanagement-2.1.0.dist-info/METADATA
featuremanagement-2.1.0.dist-info/WHEEL
featuremanagement-2.1.0.dist-info/top_level.txt
featuremanagement-2.1.0.dist-info/RECORD
