Metadata-Version: 2.4
Name: FeatureManagement
Version: 2.1.0
Summary: A library for enabling/disabling features at runtime.
Home-page: https://github.com/Azure/azure-sdk-for-python/tree/main/sdk/appconfiguration/feature-management
Author: Microsoft Corporation
Author-email: Microsoft Corporation <appconfig@microsoft.com>
License:     MIT License
Project-URL: Homepage, https://github.com/microsoft/FeatureManagement-Python
Project-URL: Issues, https://github.com/microsoft/FeatureManagement-Python/issues
Classifier: Development Status :: 5 - Production/Stable
Classifier: Programming Language :: Python
Classifier: Programming Language :: Python :: 3 :: Only
Classifier: Programming Language :: Python :: 3
Classifier: Programming Language :: Python :: 3.8
Classifier: Programming Language :: Python :: 3.9
Classifier: Programming Language :: Python :: 3.10
Classifier: Programming Language :: Python :: 3.11
Classifier: License :: OSI Approved :: MIT License
Requires-Python: >=3.6
License-File: LICENSE
Provides-Extra: azuremonitor
Requires-Dist: azure-monitor-events-extension<2.0.0; extra == "azuremonitor"
Dynamic: author
Dynamic: home-page
Dynamic: license-file
Dynamic: requires-python
